{
	"info": {
		"_postman_id": "0903d0f8-c2c2-43c4-92ae-699f855fbff5",
		"name": "Intel Hackathon",
		"schema": "https://schema.getpostman.com/json/collection/v2.1.0/collection.json",
		"_exporter_id": "25527776"
	},
	"item": [
		{
			"name": "Add user",
			"request": {
				"method": "POST",
				"header": [],
				"body": {
					"mode": "raw",
					"raw": "{\n    \"email\": \"venkadeshdeveloper@gmail.com\",\n    \"username\": \"venkadesh\",\n    \"password\": \"venkadesh\",\n    \"comments\": \"\",\n    \"products\": \"\"\n}",
					"options": {
						"raw": {
							"language": "json"
						}
					}
				},
				"url": {
					"raw": "http://127.0.0.1:5000/addUser",
					"protocol": "http",
					"host": [
						"127",
						"0",
						"0",
						"1"
					],
					"port": "5000",
					"path": [
						"addUser"
					]
				}
			},
			"response": []
		},
		{
			"name": "Add items",
			"request": {
				"method": "POST",
				"header": [],
				"body": {
					"mode": "raw",
					"raw": "{\n    \"itemID\": 1,\n    \"price\": \"500\",\n    \"productName\": \"Mouse\",\n    \"features\": [\n        \"RGB Lights\",\n        \"Smooth Scrolling\"\n    ],\n    \"comments\": \"\",\n    \"comment-users\": \"\",\n    \"imageURL\": \"https://www.meckeys.com/wp-content/uploads/2021/08/Keychron-K2-hot-swappable-wireless-mechanical-keyboard-for-Mac-Windows-iOS-Gateron-switch-blue-with-type-C-RGB-white-backlight-min.jpg\",\n    \"brought\": \"\"\n}",
					"options": {
						"raw": {
							"language": "json"
						}
					}
				},
				"url": {
					"raw": "http://127.0.0.1:5000/addItems",
					"protocol": "http",
					"host": [
						"127",
						"0",
						"0",
						"1"
					],
					"port": "5000",
					"path": [
						"addItems"
					]
				}
			},
			"response": []
		},
		{
			"name": "Check login",
			"request": {
				"method": "POST",
				"header": [],
				"body": {
					"mode": "raw",
					"raw": "{\n    \"password\": \"venkadesh\"\n}",
					"options": {
						"raw": {
							"language": "json"
						}
					}
				},
				"url": {
					"raw": "http://127.0.0.1:5000/venkadesh",
					"protocol": "http",
					"host": [
						"127",
						"0",
						"0",
						"1"
					],
					"port": "5000",
					"path": [
						"venkadesh"
					]
				}
			},
			"response": []
		},
		{
			"name": "Get items",
			"request": {
				"method": "GET",
				"header": [],
				"url": {
					"raw": "http://127.0.0.1:5000/getItems",
					"protocol": "http",
					"host": [
						"127",
						"0",
						"0",
						"1"
					],
					"port": "5000",
					"path": [
						"getItems"
					]
				}
			},
			"response": []
		},
		{
			"name": "Get specific items",
			"request": {
				"method": "GET",
				"header": [],
				"url": {
					"raw": "http://127.0.0.1:5000/getItem/2",
					"protocol": "http",
					"host": [
						"127",
						"0",
						"0",
						"1"
					],
					"port": "5000",
					"path": [
						"getItem",
						"2"
					]
				}
			},
			"response": []
		},
		{
			"name": "Add comments",
			"request": {
				"method": "POST",
				"header": [],
				"body": {
					"mode": "raw",
					"raw": "{\n    \"comments\": \"Nice Product\",\n    \"user-email\": \"venkadeshdeveloper@gmail.com\"\n}",
					"options": {
						"raw": {
							"language": "json"
						}
					}
				},
				"url": {
					"raw": "http://127.0.0.1:5000/addComments/2",
					"protocol": "http",
					"host": [
						"127",
						"0",
						"0",
						"1"
					],
					"port": "5000",
					"path": [
						"addComments",
						"2"
					]
				}
			},
			"response": []
		},
		{
			"name": "Add to Cart",
			"request": {
				"method": "POST",
				"header": [],
				"body": {
					"mode": "raw",
					"raw": "{\n    \"user-email\": \"venkadeshdeveloper@gmail.com\"\n}",
					"options": {
						"raw": {
							"language": "json"
						}
					}
				},
				"url": {
					"raw": "http://127.0.0.1:5000/addToCart/1",
					"protocol": "http",
					"host": [
						"127",
						"0",
						"0",
						"1"
					],
					"port": "5000",
					"path": [
						"addToCart",
						"1"
					]
				}
			},
			"response": []
		},
		{
			"name": "Remove from cart",
			"request": {
				"method": "POST",
				"header": [],
				"body": {
					"mode": "raw",
					"raw": "{\n    \"user-email\": \"venkadeshdeveloper@gmail.com\"\n}",
					"options": {
						"raw": {
							"language": "json"
						}
					}
				},
				"url": {
					"raw": "http://127.0.0.1:5000/removeFromCart/1",
					"protocol": "http",
					"host": [
						"127",
						"0",
						"0",
						"1"
					],
					"port": "5000",
					"path": [
						"removeFromCart",
						"1"
					]
				}
			},
			"response": []
		}
	]
}